starlette_injector/__about__.py
starlette_injector/__init__.py
starlette_injector-0.0.3.dist-info/METADATA
starlette_injector-0.0.3.dist-info/WHEEL
starlette_injector-0.0.3.dist-info/licenses/LICENSE.txt
starlette_injector-0.0.3.dist-info/RECORD
