Metadata-Version: 2.1
Name: starlette-injector
Version: 0.0.3
Project-URL: Documentation, https://github.com/kalaracey/starlette-injector#readme
Project-URL: Issues, https://github.com/kalaracey/starlette-injector/issues
Project-URL: Source, https://github.com/kalaracey/starlette-injector
Author: Kyle Laracey
License-Expression: MIT
License-File: LICENSE.txt
Classifier: Development Status :: 4 - Beta
Classifier: Programming Language :: Python
Classifier: Programming Language :: Python :: 3.7
Classifier: Programming Language :: Python :: 3.8
Classifier: Programming Language :: Python :: 3.9
Classifier: Programming Language :: Python :: 3.10
Classifier: Programming Language :: Python :: 3.11
Classifier: Programming Language :: Python :: Implementation :: CPython
Classifier: Programming Language :: Python :: Implementation :: PyPy
Requires-Python: >=3.7
Requires-Dist: injector
Requires-Dist: starlette
